StepByStepLinearRegression/__init__.py
StepByStepLinearRegression/logistic.py
StepByStepLinearRegression/multiplelinear.py
StepByStepLinearRegression/simplelinear.py
stepbysteplinearregression-0.1.1.dist-info/licenses/LICENSE
stepbysteplinearregression-0.1.1.dist-info/METADATA
stepbysteplinearregression-0.1.1.dist-info/WHEEL
stepbysteplinearregression-0.1.1.dist-info/top_level.txt
stepbysteplinearregression-0.1.1.dist-info/RECORD
