Metadata-Version: 2.4
Name: StepByStepLinearRegression
Version: 0.1.1
Summary: A package for step-by-step regression analysis including simple, multiple, and logistic regression.
Home-page: https://github.com/mellamochiao/StepByStepLinearRegression
Author: mellamochiao
Author-email: chou6855@gmail.com
Classifier: Programming Language :: Python :: 3
Classifier: License :: OSI Approved :: MIT License
Classifier: Operating System :: OS Independent
Classifier: Intended Audience :: Education
Classifier: Topic :: Scientific/Engineering :: Information Analysis
Requires-Python: >=3.7
License-File: LICENSE
Requires-Dist: numpy
Requires-Dist: pandas
Dynamic: author
Dynamic: author-email
Dynamic: classifier
Dynamic: description
Dynamic: description-content-type
Dynamic: home-page
Dynamic: license-file
Dynamic: requires-dist
Dynamic: requires-python
Dynamic: summary
